{
  "id" : 671,
  "cast" : [
    {
      "gender" : 2,
      "character" : "Harry Potter",
      "id" : 10980,
      "order" : 0,
      "cast_id" : 27,
      "profile_path" : "\/j0A7iK2wIQ1NWwJVVaTegMmKgR.jpg",
      "name" : "Daniel Radcliffe",
      "credit_id" : "52fe4267c3a36847f801be91"
    },
    {
      "gender" : 2,
      "character" : "Ron Weasley",
      "id" : 10989,
      "order" : 1,
      "cast_id" : 37,
      "profile_path" : "\/iFlkpTaOF6fGLqxz8b0PhI0i0zN.jpg",
      "name" : "Rupert Grint",
      "credit_id" : "52fe4267c3a36847f801beb9"
    },
    {
      "gender" : 1,
      "character" : "Hermione Granger",
      "id" : 10990,
      "order" : 2,
      "cast_id" : 49,
      "profile_path" : "\/mf0OANvWYSzU1d8yggrhyw8IbIz.jpg",
      "name" : "Emma Watson",
      "credit_id" : "531736ea92514138c00010a3"
    },
    {
      "gender" : 2,
      "character" : "Albus Dumbledore",
      "id" : 194,
      "order" : 3,
      "cast_id" : 23,
      "profile_path" : "\/51wDHVFNqrYgvUBMOcACAt4sJU9.jpg",
      "name" : "Richard Harris",
      "credit_id" : "52fe4267c3a36847f801be81"
    },
    {
      "gender" : 2,
      "character" : "Draco Malfoy",
      "id" : 10993,
      "order" : 4,
      "cast_id" : 41,
      "profile_path" : "\/bg5TcioIqc5Kt6CE609wXziZ9Cm.jpg",
      "name" : "Tom Felton",
      "credit_id" : "52fe4267c3a36847f801bec9"
    },
    {
      "gender" : 2,
      "character" : "Rubeus Hagrid",
      "id" : 1923,
      "order" : 5,
      "cast_id" : 25,
      "profile_path" : "\/jOHs3xvlwRiiG2CLtso5zzmGCXg.jpg",
      "name" : "Robbie Coltrane",
      "credit_id" : "52fe4267c3a36847f801be89"
    },
    {
      "gender" : 2,
      "character" : "Severus Snape",
      "id" : 4566,
      "order" : 6,
      "cast_id" : 44,
      "profile_path" : "\/7tADZs4ILE93oJ5pAh6mKQFEq2m.jpg",
      "name" : "Alan Rickman",
      "credit_id" : "52fe4267c3a36847f801bed5"
    },
    {
      "gender" : 1,
      "character" : "Minerva McGonagall",
      "id" : 10978,
      "order" : 7,
      "cast_id" : 24,
      "profile_path" : "\/pxJSXL9NELIsawroTYNQOt5JlZz.jpg",
      "name" : "Maggie Smith",
      "credit_id" : "52fe4267c3a36847f801be85"
    },
    {
      "gender" : 2,
      "character" : "Vernon Dursley",
      "id" : 10983,
      "order" : 8,
      "cast_id" : 30,
      "profile_path" : "\/EuV0DyZ5nBh3ZAUWjEqdWlt8sK.jpg",
      "name" : "Richard Griffiths",
      "credit_id" : "52fe4267c3a36847f801be9d"
    },
    {
      "gender" : 2,
      "character" : "Professor Quirrell\/Voldemort",
      "id" : 10985,
      "order" : 9,
      "cast_id" : 32,
      "profile_path" : "\/xMC8aPDwhEZcjRHEFcgytSr3BzM.jpg",
      "name" : "Ian Hart",
      "credit_id" : "52fe4267c3a36847f801bea5"
    },
    {
      "gender" : 1,
      "character" : "Petunia Dursley",
      "id" : 10981,
      "order" : 10,
      "cast_id" : 28,
      "profile_path" : "\/tjM74LcxwnYM77Csg1EtlXb1F9a.jpg",
      "name" : "Fiona Shaw",
      "credit_id" : "52fe4267c3a36847f801be95"
    },
    {
      "gender" : 2,
      "character" : "Garrick Ollivander",
      "id" : 5049,
      "order" : 11,
      "cast_id" : 35,
      "profile_path" : "\/kLW1Q53NRuB0EihduBFX3Lbtcl6.jpg",
      "name" : "John Hurt",
      "credit_id" : "52fe4267c3a36847f801beb1"
    },
    {
      "gender" : 2,
      "character" : "Argus Filch",
      "id" : 11180,
      "order" : 12,
      "cast_id" : 53,
      "profile_path" : "\/znpkwHitb3pcaJbUmgDqG0YenYp.jpg",
      "name" : "David Bradley",
      "credit_id" : "55022362c3a3685bab003478"
    },
    {
      "gender" : 2,
      "character" : "Neville Longbottom",
      "id" : 96841,
      "order" : 13,
      "cast_id" : 43,
      "profile_path" : "\/oDF0GxbLmbuZurVwdXvGn8vc78v.jpg",
      "name" : "Matthew Lewis",
      "credit_id" : "52fe4267c3a36847f801bed1"
    },
    {
      "gender" : 2,
      "character" : "Oliver Wood",
      "id" : 11179,
      "order" : 14,
      "cast_id" : 52,
      "profile_path" : "\/6g9cQWg3ikD3xboDtyF8qKdpmgl.jpg",
      "name" : "Sean Biggerstaff",
      "credit_id" : "5502218bc3a3685ba6003950"
    },
    {
      "gender" : 2,
      "character" : "Goblin Bank Teller \/ Filius Flitwick",
      "id" : 11184,
      "order" : 15,
      "cast_id" : 50,
      "profile_path" : "\/etcnzREze1PTIYhml6DwgvG5zbA.jpg",
      "name" : "Warwick Davis",
      "credit_id" : "54ecf79cc3a3680be60022eb"
    },
    {
      "gender" : 2,
      "character" : "Dudley Dursley",
      "id" : 10982,
      "order" : 16,
      "cast_id" : 29,
      "profile_path" : "\/b0pHwi2MeqxEpeWnF4Llihu53aJ.jpg",
      "name" : "Harry Melling",
      "credit_id" : "52fe4267c3a36847f801be99"
    },
    {
      "gender" : 2,
      "character" : "Fred Weasley",
      "id" : 96851,
      "order" : 17,
      "cast_id" : 154,
      "profile_path" : "\/qt9VZiasqGxRqbOLgSgoHmOGtoy.jpg",
      "name" : "James Phelps",
      "credit_id" : "58f1c6b29251412fb9004a38"
    },
    {
      "gender" : 2,
      "character" : "George Weasley",
      "id" : 140368,
      "order" : 18,
      "cast_id" : 155,
      "profile_path" : "\/rBRUVl2AZ1oz5TOSJdSKHLDPsB6.jpg",
      "name" : "Oliver Phelps",
      "credit_id" : "58f1c6bd9251412fb9004a3f"
    },
    {
      "gender" : 2,
      "character" : "Nearly Headless Nick (Sir Nicolas)",
      "id" : 8930,
      "order" : 19,
      "cast_id" : 51,
      "profile_path" : "\/kg63gNYQtGPi2fSNIvCnVAclCbi.jpg",
      "name" : "John Cleese",
      "credit_id" : "55021c2a9251413da800389e"
    },
    {
      "gender" : 2,
      "character" : "Percy Weasley",
      "id" : 10992,
      "order" : 20,
      "cast_id" : 40,
      "profile_path" : "\/bGrWreM4CeXWLJ7VulJnXoJfSgj.jpg",
      "name" : "Chris Rankin",
      "credit_id" : "52fe4267c3a36847f801bec5"
    },
    {
      "gender" : 2,
      "character" : "Dean Thomas",
      "id" : 234923,
      "order" : 21,
      "cast_id" : 152,
      "profile_path" : "\/eEVvPHmxRBcEGqtoTujncmwNDhR.jpg",
      "name" : "Alfred Enoch",
      "credit_id" : "57b42075c3a3686f6d004933"
    },
    {
      "gender" : 2,
      "character" : "Seamus Finnigan",
      "id" : 234922,
      "order" : 22,
      "cast_id" : 156,
      "profile_path" : "\/jlwr3uKGgGmcWq06u2eUEerQ3kG.jpg",
      "name" : "Devon Murray",
      "credit_id" : "58f1c6d89251412fdf00498c"
    },
    {
      "gender" : 2,
      "character" : "Vincent Crabbe",
      "id" : 956224,
      "order" : 23,
      "cast_id" : 157,
      "profile_path" : "\/2Eg3ImAsq5c5tNAyJFHcFC1lejf.jpg",
      "name" : "Jamie Waylett",
      "credit_id" : "58f1c6f49251412fdf00499c"
    },
    {
      "gender" : 2,
      "character" : "Gregory Goyle",
      "id" : 11212,
      "order" : 24,
      "cast_id" : 158,
      "profile_path" : "\/hebwDG5XsbfMaEaWJ0X6OrvlXwW.jpg",
      "name" : "Josh Herdman",
      "credit_id" : "58f1c7019251412ff4004a3b"
    },
    {
      "gender" : 1,
      "character" : "Misses Hooch",
      "id" : 20240,
      "order" : 25,
      "cast_id" : 45,
      "profile_path" : "\/jghcefdw25E5Hlz5V8SFATbFcQM.jpg",
      "name" : "Zoë Wanamaker",
      "credit_id" : "52fe4267c3a36847f801bed9"
    },
    {
      "gender" : 1,
      "character" : "Molly Weasley",
      "id" : 477,
      "order" : 26,
      "cast_id" : 42,
      "profile_path" : "\/xCZKm9eMSMrbrIl2V54B9vrklvc.jpg",
      "name" : "Julie Walters",
      "credit_id" : "52fe4267c3a36847f801becd"
    },
    {
      "gender" : 1,
      "character" : "Ginny Weasley",
      "id" : 10991,
      "order" : 27,
      "cast_id" : 39,
      "profile_path" : "\/xQGPeaIQ6KJXUFbPPW70xKCR5Ee.jpg",
      "name" : "Bonnie Wright",
      "credit_id" : "52fe4267c3a36847f801bec1"
    },
    {
      "gender" : 2,
      "character" : "Lee Jordan",
      "id" : 871100,
      "order" : 28,
      "cast_id" : 160,
      "profile_path" : "\/9IAkI7agudRLfX1qX0KQYghihtf.jpg",
      "name" : "Luke Youngblood",
      "credit_id" : "58f1c7379251412fb1004a5a"
    },
    {
      "gender" : 2,
      "character" : "Griphook",
      "id" : 10987,
      "order" : 29,
      "cast_id" : 34,
      "profile_path" : "\/42pTYfAt6qeCNoXeLunIOLSkW3U.jpg",
      "name" : "Verne Troyer",
      "credit_id" : "52fe4267c3a36847f801bead"
    },
    {
      "gender" : 2,
      "character" : "James Potter",
      "id" : 1643,
      "order" : 30,
      "cast_id" : 167,
      "profile_path" : "\/G0PGZqTjenuVTAQiib4ScU7vAI.jpg",
      "name" : "Adrian Rawlins",
      "credit_id" : "58f1c7b29251412ff4004aa3"
    },
    {
      "gender" : 1,
      "character" : "Lily Potter",
      "id" : 10988,
      "order" : 31,
      "cast_id" : 36,
      "profile_path" : "\/yVV0D1aet5FWEvfildXToOmcvkg.jpg",
      "name" : "Geraldine Somerville",
      "credit_id" : "52fe4267c3a36847f801beb5"
    },
    {
      "gender" : 1,
      "character" : "La grosse dame",
      "id" : 1220119,
      "order" : 32,
      "cast_id" : 153,
      "profile_path" : "\/l7pJk2IkXlb47QXg8Z8xq2vBjc3.jpg",
      "name" : "Elizabeth Spriggs",
      "credit_id" : "582600ebc3a368361400b475"
    },
    {
      "gender" : 2,
      "character" : "Lord Voldemort",
      "id" : 19903,
      "order" : 33,
      "cast_id" : 205,
      "profile_path" : "\/f6B04svt1I5WWwWWFd6AIu7YAfG.jpg",
      "name" : "Richard Bremmer",
      "credit_id" : "5bf9eca80e0a263ab3020c05"
    },
    {
      "gender" : 1,
      "character" : "The Grey Lady",
      "id" : 58778,
      "order" : 34,
      "cast_id" : 169,
      "profile_path" : "\/mzR6dmNI5jluErFSM1eWkOb7smI.jpg",
      "name" : "Nina Young",
      "credit_id" : "58f1c7d79251412fa9004a65"
    },
    {
      "gender" : 0,
      "character" : "The Bloody Barron",
      "id" : 10732,
      "order" : 35,
      "cast_id" : 171,
      "profile_path" : "\/ui0sfTzTnum4IkFVrLdpOsUbJDL.jpg",
      "name" : "Terence Bayler",
      "credit_id" : "58f1c8049251412fb1004afa"
    },
    {
      "gender" : 2,
      "character" : "Station Guard",
      "id" : 1815748,
      "order" : 36,
      "cast_id" : 206,
      "profile_path" : "\/tJVi0TZbqUxOHHDUaV2eExKyykC.jpg",
      "name" : "Harry Taylor",
      "credit_id" : "5bf9edd292514104d201d0a5"
    },
    {
      "gender" : 1,
      "character" : "Dimpled Woman on Train",
      "id" : 1795303,
      "order" : 37,
      "cast_id" : 207,
      "profile_path" : "\/cdItrlTcghSBIgQO5JHt27OdPbT.jpg",
      "name" : "Jean Southern",
      "credit_id" : "5bf9f09392514104cc01cb75"
    },
    {
      "gender" : 2,
      "character" : "The Sorting Hat (voice)",
      "id" : 10655,
      "order" : 38,
      "cast_id" : 48,
      "profile_path" : "\/c4i7qIuX8adXpW1SC4J3Q7HyUVG.jpg",
      "name" : "Leslie Phillips",
      "credit_id" : "52fe4267c3a36847f801bee1"
    },
    {
      "gender" : 2,
      "character" : "Fat Friar",
      "id" : 1261131,
      "order" : 39,
      "cast_id" : 170,
      "profile_path" : "\/wt7FOsSF0DDIkQnsiyQbb9G75QG.jpg",
      "name" : "Simon Fisher-Becker",
      "credit_id" : "58f1c7e49251412fb5004a31"
    },
    {
      "gender" : 2,
      "character" : "Tom",
      "id" : 10984,
      "order" : 40,
      "cast_id" : 31,
      "profile_path" : "\/f08j7CcKGKwFsCV6yEhjhb83Vuy.jpg",
      "name" : "Derek Deadman",
      "credit_id" : "52fe4267c3a36847f801bea1"
    },
    {
      "gender" : 2,
      "character" : "Firenze (voice)",
      "id" : 56650,
      "order" : 41,
      "cast_id" : 168,
      "profile_path" : "\/ou2cqhqdhfQoKVEBpIh0P3sKZti.jpg",
      "name" : "Ray Fearon",
      "credit_id" : "58f1c7c8c3a3682e95004317"
    },
    {
      "gender" : 0,
      "character" : "Susan Bones",
      "id" : 11183,
      "order" : 42,
      "cast_id" : 159,
      "profile_path" : "\/jswEVJ4diBj9eEO08hv12ZIK4Tw.jpg",
      "name" : "Eleanor Columbus",
      "credit_id" : "58f1c7149251412fc7004a37"
    },
    {
      "gender" : 0,
      "character" : "Diagon Alley Boy",
      "id" : 10986,
      "order" : 43,
      "cast_id" : 33,
      "profile_path" : null,
      "name" : "Ben Borowiecki",
      "credit_id" : "52fe4267c3a36847f801bea9"
    },
    {
      "gender" : 1,
      "character" : "Angelina Johnson",
      "id" : 1796502,
      "order" : 44,
      "cast_id" : 161,
      "profile_path" : "\/j1vSVgSWCizFtdaSOJWCiYeP45M.jpg",
      "name" : "Danielle Tabor",
      "credit_id" : "58f1c746c3a3682ede0042ea"
    },
    {
      "gender" : 1,
      "character" : "Alicia Spinnet",
      "id" : 1796505,
      "order" : 45,
      "cast_id" : 162,
      "profile_path" : "\/gUs00bCZKejc7z8xFT2Q9BEofNX.jpg",
      "name" : "Leilah Sutherland",
      "credit_id" : "58f1c75ac3a3682ee20040c5"
    },
    {
      "gender" : 0,
      "character" : "Katie Bell",
      "id" : 11185,
      "order" : 46,
      "cast_id" : 163,
      "profile_path" : null,
      "name" : "Emily Dale",
      "credit_id" : "58f1c768c3a3682ea7004475"
    },
    {
      "gender" : 0,
      "character" : "Marcus Flint",
      "id" : 1796509,
      "order" : 47,
      "cast_id" : 165,
      "profile_path" : "\/zFhZw7JUcjVTr9nfobUhkq1pRnZ.jpg",
      "name" : "Will Theakston",
      "credit_id" : "58f1c79d9251412ff4004a8c"
    },
    {
      "gender" : 2,
      "character" : "Terrence Higgs",
      "id" : 1796510,
      "order" : 48,
      "cast_id" : 166,
      "profile_path" : "\/3kBGRXEJ4KwIrRmgDUebiOxEKFs.jpg",
      "name" : "Scot Fearn",
      "credit_id" : "58f1c7a99251412fb9004af1"
    },
    {
      "gender" : 0,
      "character" : "Baby Harry Potter",
      "id" : 10979,
      "order" : 49,
      "cast_id" : 26,
      "profile_path" : null,
      "name" : "Saunders Triplets",
      "credit_id" : "52fe4267c3a36847f801be8d"
    },
    {
      "gender" : 2,
      "character" : "Goblin (uncredited)",
      "id" : 1214513,
      "order" : 50,
      "cast_id" : 61,
      "profile_path" : "\/wggqzE3RjIKh6JaboOuEuIi7lj5.jpg",
      "name" : "Jimmy Vee",
      "credit_id" : "567aa42ec3a3685bb90025e8"
    },
    {
      "gender" : 1,
      "character" : "Child at Zoo (uncredited)",
      "id" : 1639982,
      "order" : 51,
      "cast_id" : 151,
      "profile_path" : null,
      "name" : "Kieri Kennedy",
      "credit_id" : "576b0fd7925141382800037c"
    },
    {
      "gender" : 0,
      "character" : "Amanda (uncredited)",
      "id" : 1796522,
      "order" : 52,
      "cast_id" : 175,
      "profile_path" : null,
      "name" : "Christina Petrou",
      "credit_id" : "58f1c9ab9251412fc0004a90"
    },
    {
      "gender" : 0,
      "character" : "Alice (uncredited)",
      "id" : 1796523,
      "order" : 53,
      "cast_id" : 176,
      "profile_path" : null,
      "name" : "Gemma Sandzer",
      "credit_id" : "58f1c9ed9251412fb1004c93"
    },
    {
      "gender" : 1,
      "character" : "Augusta Longbottom (uncredited)",
      "id" : 430776,
      "order" : 54,
      "cast_id" : 174,
      "profile_path" : null,
      "name" : "Leila Hoffman",
      "credit_id" : "58f1c966c3a3682ee200422b"
    },
    {
      "gender" : 0,
      "character" : "Dedalus Diggle (uncredited)",
      "id" : 1796520,
      "order" : 55,
      "cast_id" : 173,
      "profile_path" : null,
      "name" : "David Brett",
      "credit_id" : "58f1c8f39251412fb1004bc2"
    },
    {
      "gender" : 0,
      "character" : "Girl in Potion Class (uncredited)",
      "id" : 1462953,
      "order" : 56,
      "cast_id" : 180,
      "profile_path" : null,
      "name" : "Zoe Sugg",
      "credit_id" : "58f1cc56c3a3682ece0044a4"
    },
    {
      "gender" : 0,
      "character" : "Septima Vector (uncredited)",
      "id" : 1796524,
      "order" : 57,
      "cast_id" : 177,
      "profile_path" : null,
      "name" : "Hazel Showham",
      "credit_id" : "58f1ca139251412fa9004bee"
    },
    {
      "gender" : 1,
      "character" : "Hogwart's student",
      "id" : 1863625,
      "order" : 58,
      "cast_id" : 265,
      "profile_path" : "\/dALgtxH89twoSL9AwKstQTC2OLO.jpg",
      "name" : "Bernadette Jane Vanderkar",
      "credit_id" : "5e32851f4ca676001a4d5120"
    },
    {
      "gender" : 1,
      "character" : "Hogwarts Schoolgirl (uncredited)",
      "id" : 143240,
      "order" : 59,
      "cast_id" : 266,
      "profile_path" : "\/s4B1sheXe3zem1H8VXd5oQ2Wu1m.jpg",
      "name" : "Julianne Hough",
      "credit_id" : "5e809ad11d6c5f00141d629a"
    }
  ],
  "crew" : [
    {
      "gender" : 2,
      "profile_path" : "\/2Ats98PB1SH2yfEPikiLdhRuXZm.jpg",
      "id" : 491,
      "job" : "Original Music Composer",
      "department" : "Sound",
      "name" : "John Williams",
      "credit_id" : "52fe4267c3a36847f801be1d"
    },
    {
      "gender" : 2,
      "profile_path" : null,
      "id" : 8380,
      "job" : "Art Direction",
      "department" : "Art",
      "name" : "Michael Lamont",
      "credit_id" : "56ed820f9251412f26000275"
    },
    {
      "gender" : 1,
      "profile_path" : null,
      "id" : 1302,
      "job" : "Casting",
      "department" : "Production",
      "name" : "Susie Figgis",
      "credit_id" : "52fe4267c3a36847f801be2f"
    },
    {
      "gender" : 2,
      "profile_path" : null,
      "id" : 2702,
      "job" : "Director of Photography",
      "department" : "Camera",
      "name" : "John Seale",
      "credit_id" : "52fe4267c3a36847f801be23"
    },
    {
      "gender" : 1,
      "profile_path" : null,
      "id" : 2874,
      "job" : "Casting",
      "department" : "Production",
      "name" : "Janet Hirshenson",
      "credit_id" : "52fe4267c3a36847f801be35"
    },
    {
      "gender" : 1,
      "profile_path" : "\/aVOlC6UkKaxZpzvpdRxCjkMtJHI.jpg",
      "id" : 3275,
      "job" : "Casting",
      "department" : "Production",
      "name" : "Jane Jenkins",
      "credit_id" : "52fe4267c3a36847f801be3b"
    },
    {
      "gender" : 2,
      "profile_path" : "\/pZUcIBbaWsX64d5Qy3SyGKcl88U.jpg",
      "id" : 6581,
      "job" : "Editor",
      "department" : "Editing",
      "name" : "Richard Francis-Bruce",
      "credit_id" : "52fe4267c3a36847f801be29"
    },
    {
      "gender" : 2,
      "profile_path" : null,
      "id" : 4755,
      "job" : "Second Unit Director",
      "department" : "Directing",
      "name" : "David R. Ellis",
      "credit_id" : "5c55e372c3a36805e882e967"
    },
    {
      "gender" : 1,
      "profile_path" : null,
      "id" : 5331,
      "job" : "Set Decoration",
      "department" : "Art",
      "name" : "Stephanie McMillan",
      "credit_id" : "52fe4267c3a36847f801be53"
    },
    {
      "gender" : 2,
      "profile_path" : "\/iI9F5WDkTrkxMHlAdq9XVXkfP3i.jpg",
      "id" : 5491,
      "job" : "Production Design",
      "department" : "Art",
      "name" : "Stuart Craig",
      "credit_id" : "52fe4267c3a36847f801be47"
    },
    {
      "gender" : 2,
      "profile_path" : null,
      "id" : 6866,
      "job" : "Unit Production Manager",
      "department" : "Production",
      "name" : "Todd Arnow",
      "credit_id" : "56ed8a25c3a3682265006f44"
    },
    {
      "gender" : 2,
      "profile_path" : null,
      "id" : 6866,
      "job" : "Associate Producer",
      "department" : "Production",
      "name" : "Todd Arnow",
      "credit_id" : "5569055fc3a36876ff0000fb"
    },
    {
      "gender" : 2,
      "profile_path" : null,
      "id" : 6870,
      "job" : "Executive Producer",
      "department" : "Production",
      "name" : "Duncan Henderson",
      "credit_id" : "556905b19251416b04000524"
    },
    {
      "gender" : 2,
      "profile_path" : null,
      "id" : 7789,
      "job" : "Art Direction",
      "department" : "Art",
      "name" : "Cliff Robinson",
      "credit_id" : "56ed8262c3a368224e007247"
    },
    {
      "gender" : 2,
      "profile_path" : "\/p7VSWFQ6V99p3jLJOrNI1NlnTrg.jpg",
      "id" : 10965,
      "job" : "Director",
      "department" : "Directing",
      "name" : "Chris Columbus",
      "credit_id" : "52fe4267c3a36847f801be05"
    },
    {
      "gender" : 2,
      "profile_path" : "\/p7VSWFQ6V99p3jLJOrNI1NlnTrg.jpg",
      "id" : 10965,
      "job" : "Executive Producer",
      "department" : "Production",
      "name" : "Chris Columbus",
      "credit_id" : "5569059a92514173b3000126"
    },
    {
      "gender" : 1,
      "profile_path" : "\/iRVpNCEUDXfjaVqDrIkukUrMHH.jpg",
      "id" : 10966,
      "job" : "Novel",
      "department" : "Writing",
      "name" : "J.K. Rowling",
      "credit_id" : "52fe4267c3a36847f801be0b"
    },
    {
      "gender" : 2,
      "profile_path" : null,
      "id" : 10967,
      "job" : "Screenplay",
      "department" : "Writing",
      "name" : "Steve Kloves",
      "credit_id" : "52fe4267c3a36847f801be11"
    },
    {
      "gender" : 2,
      "profile_path" : null,
      "id" : 10968,
      "job" : "Producer",
      "department" : "Production",
      "name" : "David Heyman",
      "credit_id" : "52fe4267c3a36847f801be17"
    },
    {
      "gender" : 1,
      "profile_path" : null,
      "id" : 10969,
      "job" : "Casting",
      "department" : "Production",
      "name" : "Karen Lindsay-Stewart",
      "credit_id" : "52fe4267c3a36847f801be41"
    },
    {
      "gender" : 2,
      "profile_path" : null,
      "id" : 10710,
      "job" : "Art Direction",
      "department" : "Art",
      "name" : "Andrew Ackland-Snow",
      "credit_id" : "52fe4267c3a36847f801be4d"
    },
    {
      "gender" : 1,
      "profile_path" : null,
      "id" : 10970,
      "job" : "Costume Design",
      "department" : "Costume & Make-Up",
      "name" : "Judianna Makovsky",
      "credit_id" : "52fe4267c3a36847f801be59"
    },
    {
      "gender" : 0,
      "profile_path" : null,
      "id" : 10971,
      "job" : "Makeup Artist",
      "department" : "Costume & Make-Up",
      "name" : "Clare Le Vesconte",
      "credit_id" : "52fe4267c3a36847f801be5f"
    },
    {
      "gender" : 2,
      "profile_path" : null,
      "id" : 10972,
      "job" : "Sound Effects Editor",
      "department" : "Sound",
      "name" : "Martin Cantwell",
      "credit_id" : "52fe4267c3a36847f801be65"
    },
    {
      "gender" : 0,
      "profile_path" : null,
      "id" : 10973,
      "job" : "Special Effects",
      "department" : "Crew",
      "name" : "Nigel Brackley",
      "credit_id" : "52fe4267c3a36847f801be6b"
    },
    {
      "gender" : 0,
      "profile_path" : null,
      "id" : 10974,
      "job" : "Visual Effects Supervisor",
      "department" : "Visual Effects",
      "name" : "Jim Berney",
      "credit_id" : "52fe4267c3a36847f801be71"
    },
    {
      "gender" : 0,
      "profile_path" : null,
      "id" : 10975,
      "job" : "Stunts",
      "department" : "Crew",
      "name" : "Henry Allen",
      "credit_id" : "52fe4267c3a36847f801be77"
    },
    {
      "gender" : 0,
      "profile_path" : null,
      "id" : 10976,
      "job" : "Stunt Coordinator",
      "department" : "Crew",
      "name" : "Greg Powell",
      "credit_id" : "52fe4267c3a36847f801be7d"
    },
    {
      "gender" : 0,
      "profile_path" : null,
      "id" : 10908,
      "job" : "Art Direction",
      "department" : "Art",
      "name" : "Peter Francis",
      "credit_id" : "56ed81f89251415e620070fd"
    },
    {
      "gender" : 2,
      "profile_path" : "\/1jXjMIPGdcyTzGtVgGmlMIYMDnD.jpg",
      "id" : 11222,
      "job" : "Executive Producer",
      "department" : "Production",
      "name" : "Mark Radcliffe",
      "credit_id" : "556905bdc3a36854890004a4"
    },
    {
      "gender" : 2,
      "profile_path" : null,
      "id" : 10788,
      "job" : "Art Direction",
      "department" : "Art",
      "name" : "Steven Lawrence",
      "credit_id" : "56ed82379251412f2600027d"
    },
    {
      "gender" : 0,
      "profile_path" : null,
      "id" : 11297,
      "job" : "Hair Designer",
      "department" : "Costume & Make-Up",
      "name" : "Eithné Fennel",
      "credit_id" : "56ed877592514171a0000a08"
    },
    {
      "gender" : 0,
      "profile_path" : null,
      "id" : 11298,
      "job" : "Makeup Designer",
      "department" : "Costume & Make-Up",
      "name" : "Amanda Knight",
      "credit_id" : "56ed87a79251413a8f004ce7"
    },
    {
      "gender" : 2,
      "profile_path" : null,
      "id" : 10612,
      "job" : "Musician",
      "department" : "Sound",
      "name" : "Peter Davies",
      "credit_id" : "594a8fc1c3a36861b500f1b3"
    },
    {
      "gender" : 2,
      "profile_path" : null,
      "id" : 40817,
      "job" : "Sound Re-Recording Mixer",
      "department" : "Sound",
      "name" : "Adam Daniel",
      "credit_id" : "56ed8cfdc3a3682265006fd9"
    },
    {
      "gender" : 0,
      "profile_path" : null,
      "id" : 11711,
      "job" : "Associate Producer",
      "department" : "Production",
      "name" : "Paula DuPré Pesmen",
      "credit_id" : "569fe34cc3a36858cb009b4e"
    },
    {
      "gender" : 2,
      "profile_path" : null,
      "id" : 12761,
      "job" : "Supervising Sound Editor",
      "department" : "Sound",
      "name" : "Eddy Joseph",
      "credit_id" : "56ed8d13c3a3682265006fdf"
    },
    {
      "gender" : 2,
      "profile_path" : null,
      "id" : 17828,
      "job" : "Executive Producer",
      "department" : "Production",
      "name" : "Michael Barnathan",
      "credit_id" : "55690584c3a3687698000132"
    },
    {
      "gender" : 2,
      "profile_path" : null,
      "id" : 24219,
      "job" : "Assistant Editor",
      "department" : "Editing",
      "name" : "Claus Wehlisch",
      "credit_id" : "5c55e741c3a368478c9f15df"
    },
    {
      "gender" : 0,
      "profile_path" : null,
      "id" : 26144,
      "job" : "Art Direction",
      "department" : "Art",
      "name" : "Lucinda Thomson",
      "credit_id" : "56ed824d9251413a8f004bd2"
    },
    {
      "gender" : 1,
      "profile_path" : null,
      "id" : 58697,
      "job" : "Co-Producer",
      "department" : "Production",
      "name" : "Tanya Seghatchian",
      "credit_id" : "556905c8c3a36854790004dc"
    },
    {
      "gender" : 0,
      "profile_path" : null,
      "id" : 66142,
      "job" : "Supervising Music Editor",
      "department" : "Sound",
      "name" : "Kenneth Wannberg",
      "credit_id" : "594a900cc3a368613c00d112"
    },
    {
      "gender" : 0,
      "profile_path" : null,
      "id" : 91480,
      "job" : "Visual Effects Coordinator",
      "department" : "Visual Effects",
      "name" : "Richard Cole",
      "credit_id" : "56ed8dabc3a3682256007619"
    },
    {
      "gender" : 0,
      "profile_path" : null,
      "id" : 101523,
      "job" : "Assistant Costume Designer",
      "department" : "Costume & Make-Up",
      "name" : "Rosemary Burrows",
      "credit_id" : "56ed87369251412f26000366"
    },
    {
      "gender" : 2,
      "profile_path" : null,
      "id" : 1020703,
      "job" : "Second Assistant Camera",
      "department" : "Camera",
      "name" : "Robert Palmer",
      "credit_id" : "5ecc5ab535818f0020bfaf5c"
    },
    {
      "gender" : 0,
      "profile_path" : null,
      "id" : 1100163,
      "job" : "Makeup Effects",
      "department" : "Crew",
      "name" : "John Lambert",
      "credit_id" : "56ed88a69251415e6200726f"
    },
    {
      "gender" : 0,
      "profile_path" : null,
      "id" : 1115279,
      "job" : "Aerial Camera",
      "department" : "Camera",
      "name" : "Simon Werry",
      "credit_id" : "594a8b7ac3a3686eba000daa"
    },
    {
      "gender" : 0,
      "profile_path" : null,
      "id" : 1122200,
      "job" : "Casting Assistant",
      "department" : "Production",
      "name" : "Buffy Hall",
      "credit_id" : "594a8edd92514145b900f636"
    },
    {
      "gender" : 0,
      "profile_path" : null,
      "id" : 1176206,
      "job" : "Production Accountant",
      "department" : "Production",
      "name" : "Gary Nixon",
      "credit_id" : "56ed8bb9c3a368226e007784"
    },
    {
      "gender" : 0,
      "profile_path" : null,
      "id" : 1294983,
      "job" : "Production Consultant",
      "department" : "Production",
      "name" : "Nisha Parti",
      "credit_id" : "5c55e9670e0a260506c6e12d"
    },
    {
      "gender" : 0,
      "profile_path" : null,
      "id" : 1322347,
      "job" : "Sound Recordist",
      "department" : "Crew",
      "name" : "Ian Munro",
      "credit_id" : "56ed898fc3a3682265006f26"
    },
    {
      "gender" : 0,
      "profile_path" : null,
      "id" : 1323295,
      "job" : "Costume Supervisor",
      "department" : "Costume & Make-Up",
      "name" : "Graham Churchyard",
      "credit_id" : "56ed8753c3a368224e007345"
    },
    {
      "gender" : 2,
      "profile_path" : null,
      "id" : 1325917,
      "job" : "Art Direction",
      "department" : "Art",
      "name" : "Simon Lamont",
      "credit_id" : "56ed8225c3a368224e00723c"
    },
    {
      "gender" : 0,
      "profile_path" : null,
      "id" : 1334489,
      "job" : "Assistant Art Director",
      "department" : "Art",
      "name" : "Dominic Masters",
      "credit_id" : "56ed83bc9251414dba0057fb"
    },
    {
      "gender" : 2,
      "profile_path" : null,
      "id" : 1335553,
      "job" : "Assistant Property Master",
      "department" : "Art",
      "name" : "Jamie Wilkinson",
      "credit_id" : "594a8b31c3a368617e00d6e2"
    },
    {
      "gender" : 0,
      "profile_path" : null,
      "id" : 1341734,
      "job" : "Temp Music Editor",
      "department" : "Crew",
      "name" : "Steve Browell",
      "credit_id" : "56ed89e99251413a8f004d55"
    },
    {
      "gender" : 0,
      "profile_path" : null,
      "id" : 1368875,
      "job" : "Production Manager",
      "department" : "Production",
      "name" : "Julie Orosz",
      "credit_id" : "56ed8be1c3a3682260007771"
    },
    {
      "gender" : 1,
      "profile_path" : null,
      "id" : 1389547,
      "job" : "Dialogue Coach",
      "department" : "Crew",
      "name" : "Sandra Frieze",
      "credit_id" : "5c55e8ebc3a36805e882f168"
    },
    {
      "gender" : 1,
      "profile_path" : null,
      "id" : 1390388,
      "job" : "Script Supervisor",
      "department" : "Directing",
      "name" : "Annie Penn",
      "credit_id" : "56ed8aa992514171a0000a9a"
    },
    {
      "gender" : 2,
      "profile_path" : "\/mEt351uRPcGWbMD1DOuDCE1c8TV.jpg",
      "id" : 1393351,
      "job" : "Scoring Mixer",
      "department" : "Sound",
      "name" : "Simon Rhodes",
      "credit_id" : "56ed8c8792514143fe0070b8"
    },
    {
      "gender" : 1,
      "profile_path" : null,
      "id" : 1393866,
      "job" : "Foley Artist",
      "department" : "Sound",
      "name" : "Felicity Cottrell",
      "credit_id" : "5c55e440c3a36826a682cccc"
    },
    {
      "gender" : 2,
      "profile_path" : null,
      "id" : 1393883,
      "job" : "Still Photographer",
      "department" : "Camera",
      "name" : "Peter Mountain",
      "credit_id" : "56ed871cc3a368225100798a"
    },
    {
      "gender" : 0,
      "profile_path" : null,
      "id" : 1394719,
      "job" : "I\/O Supervisor",
      "department" : "Visual Effects",
      "name" : "Tim Caplan",
      "credit_id" : "56ed8d75c3a368225600760a"
    },
    {
      "gender" : 0,
      "profile_path" : "\/1kskQkWzYvaDkBiXu9HBIHmo6Y2.jpg",
      "id" : 1395713,
      "job" : "Sound Mixer",
      "department" : "Sound",
      "name" : "John Midgley",
      "credit_id" : "56ed8ce8c3a36822600077ae"
    },
    {
      "gender" : 0,
      "profile_path" : null,
      "id" : 1398101,
      "job" : "Visual Effects Camera",
      "department" : "Visual Effects",
      "name" : "Andy Stevens",
      "credit_id" : "5c55e594c3a36826a682ceda"
    },
    {
      "gender" : 0,
      "profile_path" : null,
      "id" : 1401126,
      "job" : "Wigmaker",
      "department" : "Costume & Make-Up",
      "name" : "Alex Rouse",
      "credit_id" : "56ed87f19251413a8f004cfe"
    },
    {
      "gender" : 0,
      "profile_path" : null,
      "id" : 1401789,
      "job" : "Visual Effects Producer",
      "department" : "Visual Effects",
      "name" : "Joyce Cox",
      "credit_id" : "56ed8dc59251412f2600048f"
    },
    {
      "gender" : 0,
      "profile_path" : null,
      "id" : 1403634,
      "job" : "Sculptor",
      "department" : "Art",
      "name" : "Bryn Court",
      "credit_id" : "56ed84719251414dba005823"
    },
    {
      "gender" : 0,
      "profile_path" : null,
      "id" : 1404861,
      "job" : "ADR Editor",
      "department" : "Sound",
      "name" : "Nick Lowe",
      "credit_id" : "594a8f53c3a368618d00febf"
    },
    {
      "gender" : 0,
      "profile_path" : null,
      "id" : 1406789,
      "job" : "Music Editor",
      "department" : "Sound",
      "name" : "Peter Myles",
      "credit_id" : "56ed8c5f9251415e62007302"
    },
    {
      "gender" : 2,
      "profile_path" : null,
      "id" : 1407858,
      "job" : "Dialogue Editor",
      "department" : "Sound",
      "name" : "Colin Ritchie",
      "credit_id" : "5e1c8a886a300b00135e6a7a"
    },
    {
      "gender" : 2,
      "profile_path" : null,
      "id" : 1408354,
      "job" : "Camera Operator",
      "department" : "Camera",
      "name" : "Pete Cavaciuti",
      "credit_id" : "56ed86a19251413a8f004cb5"
    },
    {
      "gender" : 0,
      "profile_path" : null,
      "id" : 1408361,
      "job" : "Gaffer",
      "department" : "Lighting",
      "name" : "Kevin Edland",
      "credit_id" : "56ed8b639251412f26000433"
    },
    {
      "gender" : 0,
      "profile_path" : null,
      "id" : 1408378,
      "job" : "Assistant Sound Editor",
      "department" : "Sound",
      "name" : "Simon Chase",
      "credit_id" : "594a8f7d92514145af00f7dd"
    },
    {
      "gender" : 0,
      "profile_path" : null,
      "id" : 1411118,
      "job" : "Set Production Assistant",
      "department" : "Crew",
      "name" : "Mira Husseini",
      "credit_id" : "56ed897c92514171a0000a4f"
    },
    {
      "gender" : 0,
      "profile_path" : null,
      "id" : 1414184,
      "job" : "Animation Coordinator",
      "department" : "Visual Effects",
      "name" : "Peter Nicolai",
      "credit_id" : "5c55e67192514157df4e91bd"
    },
    {
      "gender" : 2,
      "profile_path" : null,
      "id" : 1417413,
      "job" : "Property Master",
      "department" : "Art",
      "name" : "Barry Wilkinson",
      "credit_id" : "5e1c8a986a300b00135e6a82"
    },
    {
      "gender" : 0,
      "profile_path" : null,
      "id" : 1424172,
      "job" : "Animation Supervisor",
      "department" : "Visual Effects",
      "name" : "David Andrews",
      "credit_id" : "56ed8d51c3a368226e0077d3"
    },
    {
      "gender" : 0,
      "profile_path" : "\/hYHZ71AEAZV5v24Qm0ixOSlKON9.jpg",
      "id" : 1427843,
      "job" : "Prosthetic Makeup Artist",
      "department" : "Costume & Make-Up",
      "name" : "Mark Coulier",
      "credit_id" : "594a8c8a92514145a800f131"
    },
    {
      "gender" : 0,
      "profile_path" : null,
      "id" : 1428506,
      "job" : "Steadicam Operator",
      "department" : "Camera",
      "name" : "Alf Tramontin",
      "credit_id" : "56ed8705c3a3682251007985"
    },
    {
      "gender" : 0,
      "profile_path" : null,
      "id" : 1429245,
      "job" : "Special Effects Coordinator",
      "department" : "Crew",
      "name" : "Yves De Bono",
      "credit_id" : "56ed89a59251412b3300048f"
    },
    {
      "gender" : 0,
      "profile_path" : null,
      "id" : 1431509,
      "job" : "Projection",
      "department" : "Crew",
      "name" : "Toby Lloyd",
      "credit_id" : "56ed88ccc3a368224e00739f"
    },
    {
      "gender" : 0,
      "profile_path" : null,
      "id" : 1436189,
      "job" : "Sequence Leads",
      "department" : "Crew",
      "name" : "Bob Mercier",
      "credit_id" : "56ed8df0c3a368224e007485"
    },
    {
      "gender" : 0,
      "profile_path" : null,
      "id" : 1446691,
      "job" : "First Assistant Editor",
      "department" : "Editing",
      "name" : "Jennifer Spenelli",
      "credit_id" : "56ed8b0792514143fe007077"
    },
    {
      "gender" : 2,
      "profile_path" : null,
      "id" : 1451854,
      "job" : "Additional Sound Re-Recording Mixer",
      "department" : "Sound",
      "name" : "Ryan Davis",
      "credit_id" : "594a8f17c3a36861b500f139"
    },
    {
      "gender" : 0,
      "profile_path" : null,
      "id" : 1462599,
      "job" : "CG Animator",
      "department" : "Visual Effects",
      "name" : "Hunter Athey",
      "credit_id" : "5c55e680c3a368478c9f14b6"
    },
    {
      "gender" : 0,
      "profile_path" : null,
      "id" : 1464518,
      "job" : "Visual Effects Editor",
      "department" : "Crew",
      "name" : "Nicholas Atkinson",
      "credit_id" : "56ed8a74c3a368224e0073d7"
    },
    {
      "gender" : 0,
      "profile_path" : null,
      "id" : 1465990,
      "job" : "Construction Coordinator",
      "department" : "Art",
      "name" : "Malcolm Roberts",
      "credit_id" : "56ed83fb9251414dba00580a"
    },
    {
      "gender" : 2,
      "profile_path" : null,
      "id" : 1471947,
      "job" : "First Assistant Director",
      "department" : "Directing",
      "name" : "Chris Carreras",
      "credit_id" : "594a8d9992514145a800f216"
    },
    {
      "gender" : 0,
      "profile_path" : null,
      "id" : 1484194,
      "job" : "Sequence Supervisor",
      "department" : "Crew",
      "name" : "Hilmar Koch",
      "credit_id" : "56ed8962c3a3682256007566"
    },
    {
      "gender" : 2,
      "profile_path" : null,
      "id" : 1513639,
      "job" : "Special Effects Supervisor",
      "department" : "Visual Effects",
      "name" : "John Richardson",
      "credit_id" : "56ed8d8fc3a36822600077de"
    },
    {
      "gender" : 2,
      "profile_path" : "\/wFKCmUyXm0UD5pEl7PHSBVdne6G.jpg",
      "id" : 1516453,
      "job" : "Utility Stunts",
      "department" : "Crew",
      "name" : "Gary Arthurs",
      "credit_id" : "56ed8a4d9251414dba005954"
    },
    {
      "gender" : 0,
      "profile_path" : null,
      "id" : 1535099,
      "job" : "Orchestrator",
      "department" : "Sound",
      "name" : "Edward Karam",
      "credit_id" : "56ed8c709251412b3300050c"
    },
    {
      "gender" : 0,
      "profile_path" : null,
      "id" : 1536112,
      "job" : "Dolby Consultant",
      "department" : "Sound",
      "name" : "Julian Pinn",
      "credit_id" : "56ed8e0992514143fe00710b"
    },
    {
      "gender" : 0,
      "profile_path" : null,
      "id" : 1540250,
      "job" : "ADR Recordist",
      "department" : "Sound",
      "name" : "Gareth Bull",
      "credit_id" : "5c55e41892514116fc56b766"
    },
    {
      "gender" : 0,
      "profile_path" : null,
      "id" : 1546177,
      "job" : "Standby Painter",
      "department" : "Art",
      "name" : "Paul Couch",
      "credit_id" : "56ed85a292514171a00009b1"
    },
    {
      "gender" : 0,
      "profile_path" : null,
      "id" : 1570042,
      "job" : "Rigging Gaffer",
      "department" : "Lighting",
      "name" : "Dave Ridout",
      "credit_id" : "56ed8b8fc3a368224e00741a"
    },
    {
      "gender" : 0,
      "profile_path" : null,
      "id" : 1576005,
      "job" : "Key Grip",
      "department" : "Camera",
      "name" : "Nick Ray",
      "credit_id" : "594a8bdac3a36861db010cd0"
    },
    {
      "gender" : 2,
      "profile_path" : null,
      "id" : 1576007,
      "job" : "Pilot",
      "department" : "Crew",
      "name" : "Marc Wolff",
      "credit_id" : "594a8d6d9251417ade000eac"
    },
    {
      "gender" : 0,
      "profile_path" : null,
      "id" : 1576025,
      "job" : "Color Timer",
      "department" : "Editing",
      "name" : "Peter Hunt",
      "credit_id" : "56ed8addc3a3682251007a43"
    },
    {
      "gender" : 0,
      "profile_path" : null,
      "id" : 1578657,
      "job" : "ADR Mixer",
      "department" : "Sound",
      "name" : "Gerard Roche",
      "credit_id" : "5c55e409c3a368478c9f1116"
    },
    {
      "gender" : 0,
      "profile_path" : null,
      "id" : 1591552,
      "job" : "Painter",
      "department" : "Art",
      "name" : "Larry Gooch",
      "credit_id" : "56ed8421c3a3682259006864"
    },
    {
      "gender" : 0,
      "profile_path" : null,
      "id" : 1591576,
      "job" : "Unit Publicist",
      "department" : "Crew",
      "name" : "Vanessa Davies",
      "credit_id" : "56ed8a3c9251413a8f004d60"
    },
    {
      "gender" : 0,
      "profile_path" : null,
      "id" : 1591577,
      "job" : "Video Assist Operator",
      "department" : "Crew",
      "name" : "Bob Bridges",
      "credit_id" : "56ed8a5e9251412704000502"
    },
    {
      "gender" : 0,
      "profile_path" : null,
      "id" : 1591770,
      "job" : "Assistant Production Manager",
      "department" : "Production",
      "name" : "David Carrigan",
      "credit_id" : "594a8ebcc3a368617e00d969"
    },
    {
      "gender" : 0,
      "profile_path" : null,
      "id" : 1591771,
      "job" : "Boom Operator",
      "department" : "Sound",
      "name" : "June Prinz",
      "credit_id" : "56ed8c25c3a36822590069d4"
    },
    {
      "gender" : 0,
      "profile_path" : null,
      "id" : 1592228,
      "job" : "Transportation Co-Captain",
      "department" : "Crew",
      "name" : "Brian Estabrook",
      "credit_id" : "56ed8a03c3a368226e00773d"
    },
    {
      "gender" : 0,
      "profile_path" : null,
      "id" : 1592605,
      "job" : "Best Boy Electric",
      "department" : "Lighting",
      "name" : "David Appleby",
      "credit_id" : "56ed8b1ac3a3682265006f8a"
    },
    {
      "gender" : 0,
      "profile_path" : null,
      "id" : 1593066,
      "job" : "Art Department Coordinator",
      "department" : "Art",
      "name" : "Lisa Turner",
      "credit_id" : "56ed8397c3a368224e007286"
    },
    {
      "gender" : 0,
      "profile_path" : null,
      "id" : 1593071,
      "job" : "Production Illustrator",
      "department" : "Art",
      "name" : "Cyrille Nomberg",
      "credit_id" : "56ed8442c3a3682256007467"
    },
    {
      "gender" : 0,
      "profile_path" : null,
      "id" : 1593072,
      "job" : "Set Designer",
      "department" : "Art",
      "name" : "Michael Boone",
      "credit_id" : "56ed85869251412f26000318"
    },
    {
      "gender" : 0,
      "profile_path" : null,
      "id" : 1593074,
      "job" : "First Assistant Camera",
      "department" : "Camera",
      "name" : "Ted Deason",
      "credit_id" : "56ed86c0c3a36822560074e6"
    },
    {
      "gender" : 2,
      "profile_path" : null,
      "id" : 1593075,
      "job" : "Grip",
      "department" : "Camera",
      "name" : "Peter Muncey",
      "credit_id" : "56ed86d09251414dba005890"
    },
    {
      "gender" : 0,
      "profile_path" : null,
      "id" : 1593076,
      "job" : "Hairstylist",
      "department" : "Costume & Make-Up",
      "name" : "Jane Body",
      "credit_id" : "56ed878d9251413a8f004ce2"
    },
    {
      "gender" : 0,
      "profile_path" : null,
      "id" : 1593077,
      "job" : "Supervising Carpenter",
      "department" : "Art",
      "name" : "Mark Brady",
      "credit_id" : "5c55e3f70e0a26495ae20eef"
    },
    {
      "gender" : 0,
      "profile_path" : null,
      "id" : 1593078,
      "job" : "CG Supervisor",
      "department" : "Crew",
      "name" : "Mark Lambert",
      "credit_id" : "56ed8851c3a368226e0076f2"
    },
    {
      "gender" : 0,
      "profile_path" : null,
      "id" : 1593079,
      "job" : "Chef",
      "department" : "Crew",
      "name" : "Des Petterson-Jones",
      "credit_id" : "56ed88649251414dba0058e5"
    },
    {
      "gender" : 0,
      "profile_path" : null,
      "id" : 1593080,
      "job" : "Driver",
      "department" : "Crew",
      "name" : "Warren Deluce",
      "credit_id" : "56ed8884c3a368224e007386"
    },
    {
      "gender" : 0,
      "profile_path" : null,
      "id" : 1593081,
      "job" : "Post Production Supervisor",
      "department" : "Crew",
      "name" : "Mark Marshall",
      "credit_id" : "56ed88bb9251412b3300046a"
    },
    {
      "gender" : 0,
      "profile_path" : null,
      "id" : 1593082,
      "job" : "Scenic Artist",
      "department" : "Crew",
      "name" : "David Nicoll",
      "credit_id" : "56ed8904c3a368226e007717"
    },
    {
      "gender" : 0,
      "profile_path" : null,
      "id" : 1593083,
      "job" : "Security",
      "department" : "Crew",
      "name" : "John Cheeseman",
      "credit_id" : "56ed894692514127040004dd"
    },
    {
      "gender" : 0,
      "profile_path" : null,
      "id" : 1593084,
      "job" : "Systems Administrators & Support",
      "department" : "Crew",
      "name" : "Kevin Tengan",
      "credit_id" : "56ed89d7c3a368225900695f"
    },
    {
      "gender" : 0,
      "profile_path" : null,
      "id" : 1593085,
      "job" : "Transportation Coordinator",
      "department" : "Crew",
      "name" : "Brian Hathaway",
      "credit_id" : "56ed8a14c3a3682265006f3e"
    },
    {
      "gender" : 0,
      "profile_path" : null,
      "id" : 1593093,
      "job" : "Electrician",
      "department" : "Lighting",
      "name" : "Michael Bradley",
      "credit_id" : "56ed8b4a92514171a0000abf"
    },
    {
      "gender" : 0,
      "profile_path" : null,
      "id" : 1593094,
      "job" : "Lighting Supervisor",
      "department" : "Lighting",
      "name" : "Pauline Ts'o",
      "credit_id" : "56ed8b7ec3a3682265006f9e"
    },
    {
      "gender" : 0,
      "profile_path" : null,
      "id" : 1593095,
      "job" : "Location Manager",
      "department" : "Production",
      "name" : "Keith Hatcher",
      "credit_id" : "56ed8ba5c3a368224e007420"
    },
    {
      "gender" : 0,
      "profile_path" : null,
      "id" : 1593096,
      "job" : "Production Coordinator",
      "department" : "Production",
      "name" : "Hazel Cook",
      "credit_id" : "56ed8bcec3a368226e00778a"
    },
    {
      "gender" : 0,
      "profile_path" : null,
      "id" : 1593097,
      "job" : "Production Supervisor",
      "department" : "Production",
      "name" : "Russell Lodge",
      "credit_id" : "56ed8bf5c3a3682251007a77"
    },
    {
      "gender" : 0,
      "profile_path" : null,
      "id" : 1593100,
      "job" : "Foley Mixer",
      "department" : "Sound",
      "name" : "Ed Colver",
      "credit_id" : "5c55e535c3a36805e882eb94"
    },
    {
      "gender" : 2,
      "profile_path" : null,
      "id" : 1593101,
      "job" : "Assistant Sound Engineer",
      "department" : "Sound",
      "name" : "Jake Jackson",
      "credit_id" : "5c55e43592514151a9627344"
    },
    {
      "gender" : 0,
      "profile_path" : null,
      "id" : 1593102,
      "job" : "3D Supervisor",
      "department" : "Visual Effects",
      "name" : "Alia Agha",
      "credit_id" : "56ed8d3992514143fe0070e0"
    },
    {
      "gender" : 0,
      "profile_path" : null,
      "id" : 1593103,
      "job" : "Digital Compositors",
      "department" : "Visual Effects",
      "name" : "Anita Bevelheimer",
      "credit_id" : "56ed8d63c3a3682265006ffa"
    },
    {
      "gender" : 0,
      "profile_path" : null,
      "id" : 1593105,
      "job" : "Storyboard Artist",
      "department" : "Art",
      "name" : "Adam Brockbank",
      "credit_id" : "5c55e3dc9251410e1d4e30e0"
    },
    {
      "gender" : 0,
      "profile_path" : null,
      "id" : 1621404,
      "job" : "Second Assistant Camera",
      "department" : "Camera",
      "name" : "Tobias Eedy",
      "credit_id" : "5c55e65ec3a36805e882ee20"
    },
    {
      "gender" : 0,
      "profile_path" : null,
      "id" : 1632790,
      "job" : "ADR Voice Casting",
      "department" : "Production",
      "name" : "Kyle Clark",
      "credit_id" : "5c55e6ac9251415e346636d3"
    },
    {
      "gender" : 0,
      "profile_path" : null,
      "id" : 1659138,
      "job" : "Compositing Supervisor",
      "department" : "Visual Effects",
      "name" : "Marshall Richard Krasser",
      "credit_id" : "5c55e8dbc3a36826a682d488"
    },
    {
      "gender" : 0,
      "profile_path" : null,
      "id" : 1698016,
      "job" : "Compositing Artist",
      "department" : "Visual Effects",
      "name" : "Julia Egerton",
      "credit_id" : "5c55e8c90e0a26567ac75b8c"
    },
    {
      "gender" : 0,
      "profile_path" : null,
      "id" : 1715548,
      "job" : "Costume Coordinator",
      "department" : "Costume & Make-Up",
      "name" : "Martin Mandeville",
      "credit_id" : "594a8c50c3a368619b00e04b"
    },
    {
      "gender" : 0,
      "profile_path" : null,
      "id" : 1721858,
      "job" : "Additional Visual Effects",
      "department" : "Visual Effects",
      "name" : "Matthew Glen",
      "credit_id" : "5c55e5670e0a260506c6dbb3"
    },
    {
      "gender" : 0,
      "profile_path" : null,
      "id" : 1738171,
      "job" : "Tailor",
      "department" : "Costume & Make-Up",
      "name" : "Lee Clayton",
      "credit_id" : "594a8cb99251417ade000e21"
    },
    {
      "gender" : 0,
      "profile_path" : null,
      "id" : 1749925,
      "job" : "Visual Effects Production Manager",
      "department" : "Visual Effects",
      "name" : "Lauren A. Littleton",
      "credit_id" : "5c55e5d692514151a96278f9"
    },
    {
      "gender" : 0,
      "profile_path" : null,
      "id" : 1767782,
      "job" : "ADR Voice Casting",
      "department" : "Production",
      "name" : "Louis Elman",
      "credit_id" : "594a8e5e92514145af00f6da"
    },
    {
      "gender" : 0,
      "profile_path" : null,
      "id" : 1767785,
      "job" : "Foley Editor",
      "department" : "Sound",
      "name" : "Peter Holt",
      "credit_id" : "594a8fa0c3a3686eba0010ed"
    },
    {
      "gender" : 2,
      "profile_path" : null,
      "id" : 1796507,
      "job" : "Stunt Double",
      "department" : "Crew",
      "name" : "David Holmes",
      "credit_id" : "5c55e6029251415e346635f9"
    },
    {
      "gender" : 0,
      "profile_path" : null,
      "id" : 1836787,
      "job" : "Animal Coordinator",
      "department" : "Crew",
      "name" : "Gary Gero",
      "credit_id" : "594a8cf3c3a368617e00d826"
    },
    {
      "gender" : 0,
      "profile_path" : null,
      "id" : 1836882,
      "job" : "Dolly Grip",
      "department" : "Camera",
      "name" : "Gary Romaine",
      "credit_id" : "594a8bae92514145af00f4bb"
    },
    {
      "gender" : 0,
      "profile_path" : null,
      "id" : 1836883,
      "job" : "Digital Effects Producer",
      "department" : "Crew",
      "name" : "James Lamb",
      "credit_id" : "594a8d49c3a36861db010e08"
    },
    {
      "gender" : 0,
      "profile_path" : null,
      "id" : 1836887,
      "job" : "Second Assistant Director",
      "department" : "Directing",
      "name" : "Michael Stevenson",
      "credit_id" : "594a8df392514145b900f57d"
    },
    {
      "gender" : 0,
      "profile_path" : null,
      "id" : 1836888,
      "job" : "Third Assistant Director",
      "department" : "Directing",
      "name" : "Michael Michael",
      "credit_id" : "594a8e0fc3a368617e00d8d0"
    },
    {
      "gender" : 0,
      "profile_path" : null,
      "id" : 1836893,
      "job" : "Assistant Production Coordinator",
      "department" : "Production",
      "name" : "Alison Odell",
      "credit_id" : "594a8e84c3a368617e00d934"
    },
    {
      "gender" : 0,
      "profile_path" : null,
      "id" : 1836898,
      "job" : "Lead Animator",
      "department" : "Visual Effects",
      "name" : "Ivor Middleton",
      "credit_id" : "594a90b1c3a36861b500f27b"
    },
    {
      "gender" : 0,
      "profile_path" : null,
      "id" : 1838780,
      "job" : "Digital Color Timer",
      "department" : "Editing",
      "name" : "Paul McGhee",
      "credit_id" : "5c55e7560e0a26031bc6e3df"
    },
    {
      "gender" : 0,
      "profile_path" : null,
      "id" : 2048503,
      "job" : "Libra Head Technician",
      "department" : "Camera",
      "name" : "Joe Buxton",
      "credit_id" : "5c55e64c0e0a26567ac75425"
    },
    {
      "gender" : 0,
      "profile_path" : null,
      "id" : 2093470,
      "job" : "Contact Lens Technician",
      "department" : "Costume & Make-Up",
      "name" : "Jemma Scott-Knox-Gore",
      "credit_id" : "5c55e2cf92514157df4e8d95"
    },
    {
      "gender" : 0,
      "profile_path" : null,
      "id" : 2146042,
      "job" : "Hairdresser",
      "department" : "Costume & Make-Up",
      "name" : "Darlene Forrester",
      "credit_id" : "5c55e2ed0e0a26031bc6da53"
    },
    {
      "gender" : 0,
      "profile_path" : null,
      "id" : 2151815,
      "job" : "Special Effects Assistant",
      "department" : "Crew",
      "name" : "Kevin Wescott",
      "credit_id" : "5c55e545c3a368478c9f12fe"
    },
    {
      "gender" : 0,
      "profile_path" : null,
      "id" : 2153564,
      "job" : "Special Effects Technician",
      "department" : "Crew",
      "name" : "Michael Durkan",
      "credit_id" : "5c55e557c3a368424682d1d0"
    },
    {
      "gender" : 0,
      "profile_path" : null,
      "id" : 2198741,
      "job" : "Additional Second Assistant Director",
      "department" : "Directing",
      "name" : "R.J. Mino",
      "credit_id" : "5c55e30ac3a3687290876308"
    },
    {
      "gender" : 0,
      "profile_path" : null,
      "id" : 2215665,
      "job" : "Head of Production",
      "department" : "Production",
      "name" : "Michael Elson",
      "credit_id" : "5c55e92ec3a3687290876b8f"
    },
    {
      "gender" : 0,
      "profile_path" : null,
      "id" : 2230771,
      "job" : "Production Secretary",
      "department" : "Production",
      "name" : "Katie Reynolds",
      "credit_id" : "5c55e9929251410e1d4e3c2b"
    },
    {
      "gender" : 0,
      "profile_path" : null,
      "id" : 2230778,
      "job" : "Digital Film Recording",
      "department" : "Visual Effects",
      "name" : "Jim Davey",
      "credit_id" : "5c55e9100e0a260506c6e0cf"
    },
    {
      "gender" : 0,
      "profile_path" : null,
      "id" : 2232916,
      "job" : "Dressing Prop",
      "department" : "Art",
      "name" : "Paul Burges",
      "credit_id" : "5c55e3909251410e1d4e309f"
    },
    {
      "gender" : 0,
      "profile_path" : null,
      "id" : 2232946,
      "job" : "Senior Modeller",
      "department" : "Visual Effects",
      "name" : "John Weller",
      "credit_id" : "5c55e9b30e0a26494de05395"
    },
    {
      "gender" : 0,
      "profile_path" : null,
      "id" : 2233029,
      "job" : "Costume Assistant",
      "department" : "Costume & Make-Up",
      "name" : "Laura Johnson",
      "credit_id" : "5c55e2e20e0a2601d6d02ecb"
    },
    {
      "gender" : 0,
      "profile_path" : null,
      "id" : 2233031,
      "job" : "Additional Third Assistant Director",
      "department" : "Directing",
      "name" : "Ian Dray",
      "credit_id" : "5c55e358c3a368478c9f102f"
    },
    {
      "gender" : 0,
      "profile_path" : null,
      "id" : 2233034,
      "job" : "Continuity",
      "department" : "Directing",
      "name" : "Charlotte Mason-Apps",
      "credit_id" : "5c55e3629251415e34662ea6"
    },
    {
      "gender" : 0,
      "profile_path" : null,
      "id" : 2233036,
      "job" : "Construction Buyer",
      "department" : "Art",
      "name" : "Patrick Casey",
      "credit_id" : "5c55e3830e0a260506c6d9a6"
    },
    {
      "gender" : 0,
      "profile_path" : null,
      "id" : 2233037,
      "job" : "Head Carpenter",
      "department" : "Art",
      "name" : "Graham Weames",
      "credit_id" : "5c55e3a0c3a368478c9f1086"
    },
    {
      "gender" : 0,
      "profile_path" : null,
      "id" : 2233038,
      "job" : "Petty Cash Buyer",
      "department" : "Art",
      "name" : "Lizzi Wilson",
      "credit_id" : "5c55e3afc3a368424682cf25"
    },
    {
      "gender" : 0,
      "profile_path" : null,
      "id" : 2233043,
      "job" : "Visual Effects Production Assistant",
      "department" : "Visual Effects",
      "name" : "Allison Coit",
      "credit_id" : "5c55e5b19251410e24681ab1"
    },
    {
      "gender" : 0,
      "profile_path" : null,
      "id" : 2233044,
      "job" : "Assistant Camera",
      "department" : "Camera",
      "name" : "Janos Jersch",
      "credit_id" : "5c55e610c3a368478c9f1414"
    },
    {
      "gender" : 0,
      "profile_path" : null,
      "id" : 2233045,
      "job" : "Camera Trainee",
      "department" : "Camera",
      "name" : "Alan Harrison",
      "credit_id" : "5c55e61dc3a368478c9f1421"
    },
    {
      "gender" : 0,
      "profile_path" : null,
      "id" : 2233049,
      "job" : "Wardrobe Assistant",
      "department" : "Costume & Make-Up",
      "name" : "Anabel Campbell",
      "credit_id" : "5c55e726c3a3680b5785bc1b"
    },
    {
      "gender" : 0,
      "profile_path" : null,
      "id" : 2233051,
      "job" : "Post Production Coordinator",
      "department" : "Production",
      "name" : "Jessie Thiele Schroeder",
      "credit_id" : "5c55e7d10e0a26494de05141"
    },
    {
      "gender" : 0,
      "profile_path" : null,
      "id" : 2233053,
      "job" : "Assistant Location Manager",
      "department" : "Production",
      "name" : "Simon Burgess",
      "credit_id" : "5c55e7f69251410e24682207"
    },
    {
      "gender" : 0,
      "profile_path" : null,
      "id" : 2233054,
      "job" : "Location Assistant",
      "department" : "Production",
      "name" : "Chris Bogle",
      "credit_id" : "5c55e823c3a3680b5785bd8c"
    },
    {
      "gender" : 0,
      "profile_path" : null,
      "id" : 2233055,
      "job" : "Location Coordinator",
      "department" : "Production",
      "name" : "Sue Binfield",
      "credit_id" : "5c55e847c3a368424682d508"
    },
    {
      "gender" : 0,
      "profile_path" : null,
      "id" : 2233056,
      "job" : "Assistant Accountant",
      "department" : "Production",
      "name" : "Trevor Chalmers",
      "credit_id" : "5c55e868c3a3687199822c9a"
    },
    {
      "gender" : 0,
      "profile_path" : null,
      "id" : 2233057,
      "job" : "CG Artist",
      "department" : "Visual Effects",
      "name" : "Will Broadbent",
      "credit_id" : "5c55e8b7c3a3687199822d16"
    },
    {
      "gender" : 2,
      "profile_path" : null,
      "id" : 2233058,
      "job" : "Floor Runner",
      "department" : "Crew",
      "name" : "Chuck Douglas",
      "credit_id" : "5c55e91e0e0a265e19d336d9"
    },
    {
      "gender" : 0,
      "profile_path" : null,
      "id" : 2233059,
      "job" : "Matte Painter",
      "department" : "Visual Effects",
      "name" : "Andrew Garnet-Lawson",
      "credit_id" : "5c55e94c0e0a2601d6d03cdc"
    },
    {
      "gender" : 0,
      "profile_path" : null,
      "id" : 2233060,
      "job" : "Production Assistant",
      "department" : "Production",
      "name" : "Mark Axtell",
      "credit_id" : "5c55e95ac3a36826a682d505"
    },
    {
      "gender" : 0,
      "profile_path" : null,
      "id" : 2233061,
      "job" : "Production Executive",
      "department" : "Production",
      "name" : "Joel Román Mendías",
      "credit_id" : "5c55e98692514151a9627dac"
    },
    {
      "gender" : 0,
      "profile_path" : null,
      "id" : 2233062,
      "job" : "Rotoscoping Artist",
      "department" : "Visual Effects",
      "name" : "Martin Cook",
      "credit_id" : "5c55e9a692514157df4e96d5"
    }
  ]
}
